papers/__init__.py
papers/__main__.py
papers/_version.py
papers/bib.py
papers/config.py
papers/duplicate.py
papers/encoding.py
papers/extract.py
papers/filename.py
papers/latexenc.py
papers/utils.py
papers_cli-2.15.3.dist-info/licenses/LICENSE
papers_cli-2.15.3.dist-info/METADATA
papers_cli-2.15.3.dist-info/WHEEL
papers_cli-2.15.3.dist-info/entry_points.txt
papers_cli-2.15.3.dist-info/top_level.txt
papers_cli-2.15.3.dist-info/RECORD
