Metadata-Version: 2.4
Name: papers-cli
Version: 2.15.3
Summary: utilities to keep your PDF library organized
Author-email: Mahé Perrette <mahe.perrette@gmail.com>
License: MIT
Project-URL: homepage, https://github.com/perrette/papers
Keywords: bibtex,references,bibliography
Classifier: Programming Language :: Python :: 3
Requires-Python: >=3.9
License-File: LICENSE
Requires-Dist: PyMuPDF
Requires-Dist: unidecode
Requires-Dist: crossrefapi
Requires-Dist: bibtexparser
Requires-Dist: scholarly
Requires-Dist: rapidfuzz
Requires-Dist: python-slugify
Requires-Dist: bs4
Dynamic: license-file
